{
  "Igneous (frozen from melt)": {
    "By where they solidify": {
      "Intrusive (plutonic) - cool slowly underground \u2192 coarse-grained": ["Granite", "granodiorite", "tonalite", "diorite", "monzonite", "syenite", "gabbro", "anorthosite", "peridotite"],
      "Extrusive (volcanic) - cool quickly at/near surface \u2192 fine-grained": ["Rhyolite", "dacite", "andesite", "basalt", "komatiite (rare/ancient)"],
      "Hypabyssal (shallow intrusions) - often porphyritic": ["Microdiorite", "dolerite/diabase", "microgranite"]
    },
    "By composition (silica & alkalis)": {
      "Felsic": ["rhyolite \u2194 granite (quartz + K-feldspar rich)"],
      "Intermediate": ["andesite \u2194 diorite"],
      "Mafic": ["basalt \u2194 gabbro (pyroxene + Ca-plagioclase)"],
      "Ultramafic": ["peridotite", "dunite", "pyroxenite", "komatiite"],
      "Alkaline series": ["trachyte \u2194 syenite", "phonolite \u2194 nepheline syenite"],
      "Ultrapotassic & exotic": ["lamprophyre", "lamproite", "kimberlite", "carbonatite"]
    },
    "By texture": {
      "Phaneritic (coarse)": [],
      "Aphanitic (fine)": [],
      "Porphyritic": [],
      "Pegmatitic": [],
      "Glassy (obsidian)": [],
      "Vesicular (scoria, pumice)": [],
      "Amygdaloidal": [],
      "Pyroclastic/volcaniclastic (eruption-broken)": {
        "Tephra (loose) \u2192 tuff (lithified ash)": [],
        "Lapillistone": [],
        "Agglomerate/volcanic breccia": [],
        "Ignimbrite (welded ash-flow tuff)": []
      },
      "Special": ["pillow basalt", "spilitized basalt", "ophiolite suites (layered mafic\u2013ultramafic sequences)"]
    }
  },
  "Sedimentary (made from pre-existing material or precipitates)": {
    "By how they form": {
      "Clastic (siliciclastic)": {
        "Gravel-sized": ["conglomerate (rounded)", "breccia (angular)"],
        "Sand-sized": ["sandstone (quartz arenite, arkose, lithic sandstone; subarkose/sub-litharenite)"],
        "Silt-sized": ["siltstone"],
        "Clay-sized": ["mudstone", "shale (fissile)", "claystone"]
      },
      "Biochemical/Biogenic": {
        "Limestone/dolostone families": ["fossiliferous limestone", "micrite", "sparite", "coquina", "chalk", "oolitic limestone", "travertine"],
        "Chert (siliceous)": [],
        "Diatomite": [],
        "Radiolarite": [],
        "Coal series": ["peat", "lignite", "bituminous", "anthracite", "oil shale"]
      },
      "Chemical precipitates": {
        "Evaporites": ["rock salt (halite)", "gypsum/anhydrite", "potash salts"],
        "Iron formations": ["banded iron formation (BIF)", "ironstone"],
        "Phosphorite": []
      },
      "Volcaniclastic (reworked volcanic debris)": ["tuffaceous sandstone", "lahar deposits"],
      "Other/diagenetic features": ["concretions", "nodules", "stylolites", "cross-bedding", "ripple marks"]
    }
  },
  "Metamorphic (changed by heat, pressure, fluids)": {
    "By fabric": {
      "Foliated": ["Slate \u2192 phyllite \u2192 schist \u2192 gneiss (increasing grade)", "Migmatite (partially melted, mixed igneous\u2013metamorphic)"],
      "Non-foliated": ["Marble (from limestone/dolostone)", "Quartzite (from sandstone)", "Hornfels (contact metamorphism)", "Amphibolite (from mafic rocks)", "Serpentinite (from ultramafics)", "Eclogite", "blueschist", "greenschist (often listed by facies name)"]
    },
    "By metamorphic process/environment": {
      "Regional (mountain belts)": ["greenschist \u2192 amphibolite \u2192 granulite facies"],
      "High-pressure/low-T": ["blueschist", "eclogite (subduction)"],
      "Contact/thermal": ["hornfels", "spotted rock", "sanidinite facies"],
      "Hydrothermal/metasomatic": ["skarn", "greisen", "listvenite"],
      "Dynamic/cataclastic (fault zones)": ["cataclasite", "fault breccia", "mylonite", "ultramylonite"]
    }
  },
  "Special rock groups": {
    "Impactites": ["suevite", "impact melt rock", "shocked quartz\u2013bearing breccias"],
    "Evaporite-dominated sequences": ["halite", "gypsum/anhydrite with interbeds"],
    "Bauxites/ laterites": ["residual ores; often treated as ores/soils rather than classical rock types"],
    "Tectonites": ["rocks classified by deformation fabric (S-tectonites, L-tectonites, LS-tectonites)"]
  },
  "Quick name finder": {
    "Granite family": ["granite", "granodiorite", "tonalite", "pegmatite", "aplite"],
    "Basalt/gabbro family": ["tholeiitic basalt", "alkali basalt", "gabbro", "norite", "troctolite", "dolerite/diabase"],
    "Alkaline suite": ["syenite", "monzonite", "trachyte", "phonolite", "nepheline syenite"],
    "Ultramafic": ["peridotite (harzburgite, lherzolite, dunite)", "pyroxenite", "hornblendite"],
    "Sandstones": ["quartz arenite", "arkose", "litharenite", "greywacke"],
    "Limestones": ["fossiliferous", "oolitic", "chalk", "coquina", "micrite", "travertine"],
    "Coal": ["lignite", "sub-bituminous", "bituminous", "anthracite"],
    "Foliated metamorphics": ["slate", "phyllite", "schist", "gneiss", "migmatite"],
    "Non-foliated metamorphics": ["marble", "quartzite", "hornfels", "amphibolite", "eclogite", "serpentinite"]
  }
}
